odoo/addons/partner_address_hide_pdf_fields/README.rst
odoo/addons/partner_address_hide_pdf_fields/__init__.py
odoo/addons/partner_address_hide_pdf_fields/__manifest__.py
odoo/addons/partner_address_hide_pdf_fields/i18n/es.po
odoo/addons/partner_address_hide_pdf_fields/models/__init__.py
odoo/addons/partner_address_hide_pdf_fields/models/ir_qweb_field_contact.py
odoo/addons/partner_address_hide_pdf_fields/models/res_partner.py
odoo/addons/partner_address_hide_pdf_fields/readme/CONFIGURE.md
odoo/addons/partner_address_hide_pdf_fields/readme/CONTRIBUTORS.md
odoo/addons/partner_address_hide_pdf_fields/readme/DESCRIPTION.md
odoo/addons/partner_address_hide_pdf_fields/readme/INSTALL.md
odoo/addons/partner_address_hide_pdf_fields/readme/USAGE.md
odoo/addons/partner_address_hide_pdf_fields/static/description/icon.png
odoo/addons/partner_address_hide_pdf_fields/static/description/index.html
odoo/addons/partner_address_hide_pdf_fields/tests/__init__.py
odoo/addons/partner_address_hide_pdf_fields/tests/fake_models.py
odoo/addons/partner_address_hide_pdf_fields/tests/test_partner_address_hide_pdf_fields.py
odoo/addons/partner_address_hide_pdf_fields/views/res_country_views.xml
odoo_addon_partner_address_hide_pdf_fields-18.0.1.1.0.dist-info/METADATA
odoo_addon_partner_address_hide_pdf_fields-18.0.1.1.0.dist-info/WHEEL
odoo_addon_partner_address_hide_pdf_fields-18.0.1.1.0.dist-info/top_level.txt
odoo_addon_partner_address_hide_pdf_fields-18.0.1.1.0.dist-info/RECORD
