Metadata-Version: 2.1
Name: odoo-addon-partner_address_hide_pdf_fields
Version: 18.0.1.1.0
Requires-Python: >=3.10
Requires-Dist: odoo==18.0.*
Summary: Base module to hide new partner address fields in pdf
Home-page: https://github.com/sygel-technology/sy-partner-contact
License: AGPL-3
Author: Sygel
Classifier: Programming Language :: Python
Classifier: Framework :: Odoo
Classifier: Framework :: Odoo :: 18.0
Classifier: License :: OSI Approved :: GNU Affero General Public License v3
